ogre_cli/__init__.py
ogre_cli/app.py
ogre_cli/docker_management/__init__.py
ogre_cli/docker_management/commands.py
ogre_cli/docker_management/constants.py
ogre_cli/docker_management/gui/.streamlit/config.toml
ogre_cli/docker_management/gui/__init__.py
ogre_cli/docker_management/gui/gui.py
ogre_cli/docker_management/gui/images/ogarantia_logoBlue.png
ogre_cli/docker_management/gui/images/ogarantia_logoBlue_nameBlack.png
ogre_cli/docker_management/gui/images/ogre-run-1.png
ogre_cli/docker_management/gui/images/ogre-run-logo.png
ogre_cli/docker_management/gui/images/ogre-run.png
ogre_cli/docker_management/gui/utils.py
ogre_cli/docker_management/imports.py
ogre_cli/docker_management/subcommands.py
ogre_cli/docker_management/utilities.py
ogre_cli/menu.py
ogre_cli/tests/high_level_tests/test_import.py
ogre_cli-0.8.2.dist-info/LICENSE
ogre_cli-0.8.2.dist-info/METADATA
ogre_cli-0.8.2.dist-info/WHEEL
ogre_cli-0.8.2.dist-info/entry_points.txt
ogre_cli-0.8.2.dist-info/RECORD
