Metadata-Version: 2.1
Name: ogre_cli
Version: 0.8.2
Summary: ogre.run: code dependency hypervisor
Author: Wilder Lopes
Author-email: wilder@ogre.run
Requires-Python: >=3.8,<4.0
Classifier: Programming Language :: Python :: 3
Classifier: Programming Language :: Python :: 3.8
Classifier: Programming Language :: Python :: 3.9
Classifier: Programming Language :: Python :: 3.10
Classifier: Programming Language :: Python :: 3.11
Requires-Dist: build (>=0.9.0,<0.10.0)
Requires-Dist: docker (>=5.0.3,<6.0.0)
Requires-Dist: isort (>=5.10.1,<6.0.0)
Requires-Dist: jupyter (>=1.0.0,<2.0.0)
Requires-Dist: notebook (==6.5.5)
Requires-Dist: ogarantia-streamlit-card (>=0.0.2,<0.0.3)
Requires-Dist: psutil (>=5.9.0,<6.0.0)
Requires-Dist: pyfiglet (>=0.8.post1,<0.9)
Requires-Dist: requests (>=2.28.1,<3.0.0)
Requires-Dist: rich (>=12.4.0,<13.0.0)
Requires-Dist: upstride-argparse (>=1.0.0,<2.0.0)
Requires-Dist: yaspin (>=2.1.0,<3.0.0)
